chaingang/__init__.py
chaingang/selection_chaining.py
chaingang-0.0.2.dist-info/METADATA
chaingang-0.0.2.dist-info/WHEEL
chaingang-0.0.2.dist-info/top_level.txt
chaingang-0.0.2.dist-info/RECORD
